statefulpy/__init__.py
statefulpy/cli.py
statefulpy/config.py
statefulpy/decorator.py
statefulpy/backends/__init__.py
statefulpy/backends/base.py
statefulpy/backends/redis.py
statefulpy/backends/sqlite.py
statefulpy/serializers/__init__.py
statefulpy/serializers/base.py
statefulpy/serializers/json_serializer.py
statefulpy/serializers/pickle_serializer.py
statefulpy-0.1.3.dist-info/licenses/LICENSE
statefulpy-0.1.3.dist-info/METADATA
statefulpy-0.1.3.dist-info/WHEEL
statefulpy-0.1.3.dist-info/entry_points.txt
statefulpy-0.1.3.dist-info/top_level.txt
statefulpy-0.1.3.dist-info/RECORD
