Metadata-Version: 2.4
Name: statefulpy
Version: 0.1.3
Summary: Transparent persistent state management for Python functions
Author: StatefulPy Team
Author-email: StatefulPy Team <info@statefulpy.org>
License: MIT
Project-URL: Homepage, https://github.com/statefulpy/statefulpy
Project-URL: Documentation, https://statefulpy.readthedocs.io/
Project-URL: Bug Tracker, https://github.com/statefulpy/statefulpy/issues
Project-URL: Source Code, https://github.com/statefulpy/statefulpy
Classifier: Development Status :: 4 - Beta
Classifier: Intended Audience :: Developers
Classifier: License :: OSI Approved :: MIT License
Classifier: Programming Language :: Python :: 3
Classifier: Programming Language :: Python :: 3.8
Classifier: Programming Language :: Python :: 3.9
Classifier: Programming Language :: Python :: 3.10
Classifier: Programming Language :: Python :: 3.11
Classifier: Programming Language :: Python :: 3.12
Requires-Python: >=3.8
License-File: LICENSE
Requires-Dist: portalocker>=2.0.0
Provides-Extra: redis
Requires-Dist: redis>=4.0.0; extra == "redis"
Provides-Extra: test
Requires-Dist: pytest>=7.0.0; extra == "test"
Requires-Dist: pytest-cov>=4.0.0; extra == "test"
Requires-Dist: redis>=4.0.0; extra == "test"
Provides-Extra: dev
Requires-Dist: black>=23.0.0; extra == "dev"
Requires-Dist: isort>=5.0.0; extra == "dev"
Requires-Dist: flake8>=6.0.0; extra == "dev"
Requires-Dist: mypy>=1.0.0; extra == "dev"
Requires-Dist: build>=0.10.0; extra == "dev"
Requires-Dist: twine>=4.0.0; extra == "dev"
Requires-Dist: redis>=4.0.0; extra == "dev"
Provides-Extra: docs
Requires-Dist: sphinx>=6.0.0; extra == "docs"
Requires-Dist: sphinx-rtd-theme>=1.0.0; extra == "docs"
Dynamic: license-file
